README.md
setup.cfg
setup.py
dsmlbootcamp4/__init__.py
dsmlbootcamp4/hi.py
dsmlbootcamp4.egg-info/PKG-INFO
dsmlbootcamp4.egg-info/SOURCES.txt
dsmlbootcamp4.egg-info/dependency_links.txt
dsmlbootcamp4.egg-info/top_level.txt
dsmlbootcamp4/data_prep/__init__.py
dsmlbootcamp4/data_prep/data_prep.py
dsmlbootcamp4/eda/__init__.py
dsmlbootcamp4/eda/eda.py
dsmlbootcamp4/eda/helpers.py